aimlufotech/AimlParser.py
aimlufotech/DefaultSubs.py
aimlufotech/InMemorySessionManager.py
aimlufotech/Kernel.py
aimlufotech/PatternMgr.py
aimlufotech/Utils.py
aimlufotech/WordSub.py
aimlufotech/__init__.py
aimlufotech-0.0.2.dist-info/LICENSE
aimlufotech-0.0.2.dist-info/METADATA
aimlufotech-0.0.2.dist-info/WHEEL
aimlufotech-0.0.2.dist-info/top_level.txt
aimlufotech-0.0.2.dist-info/RECORD
